{
    "alumnos": [
        {
            "id": "01",
            "dni": "43.111.222",    
            "PadreMadreTutor":"Pedro Gómez",
            "materia": "Matemática",
            "direccion": "CalleFalsa 123",
            "imagen": "./img/id1_certificado.png"
        },

        {
            "id": "02",
            "dni": "44.123.555",
            "PadreMadreTutor":"Ana Pérez",
            "materia": "Matemática",
            "direccion": "CalleNoReal 365",
            "imagen": "./img/id2_certificado.png"
        },

        {
            "id": "03",
            "dni": "45.789.312",
            "PadreMadreTutor":"Carlos López",
            "materia": "Matemática",
            "direccion": "CalleInventada 321",
            "imagen": "./img/id3_certificado.png"
        }
    ]
}
